checuioscars1/oscars.py
checuioscars1/settings.py
checuioscars1-0.0.6.dist-info/METADATA
checuioscars1-0.0.6.dist-info/WHEEL
checuioscars1-0.0.6.dist-info/RECORD
