Metadata-Version: 2.1
Name: checuioscars1
Version: 0.0.6
Summary: My customized ORM on Oscars
Project-URL: Homepage, https://github.com/Checui/IBD_oscars
Project-URL: Bug Tracker, https://github.com/Checui/IBD_oscars/issues
Author-email: checui <che.cui@upm.es>
Classifier: License :: OSI Approved :: MIT License
Classifier: Operating System :: OS Independent
Classifier: Programming Language :: Python :: 3
Requires-Python: >=3.9
